{
  "lastUpdated": "2026-06-14T01:42:13.410Z",
  "items": [
    {
      "url": "https://www.k-bid.com/auction/62482/item/3",
      "itemName": "Error: Could not fetch",
      "currentPrice": "N/A",
      "timestamp": "2026-06-14T01:42:19.734Z",
      "error": "Request failed with status code 403"
    },
    {
      "url": "https://www.k-bid.com/auction/62482/item/4",
      "itemName": "Error: Could not fetch",
      "currentPrice": "N/A",
      "timestamp": "2026-06-14T01:42:27.818Z",
      "error": "Request failed with status code 403"
    },
    {
      "url": "https://www.k-bid.com/auction/62483/item/3",
      "itemName": "Error: Could not fetch",
      "currentPrice": "N/A",
      "timestamp": "2026-06-14T01:42:35.900Z",
      "error": "Request failed with status code 403"
    },
    {
      "url": "https://www.k-bid.com/auction/62483/item/4",
      "itemName": "Error: Could not fetch",
      "currentPrice": "N/A",
      "timestamp": "2026-06-14T01:42:43.984Z",
      "error": "Request failed with status code 403"
    },
    {
      "url": "https://www.k-bid.com/auction/62603/item/14",
      "itemName": "Error: Could not fetch",
      "currentPrice": "N/A",
      "timestamp": "2026-06-14T01:42:52.067Z",
      "error": "Request failed with status code 403"
    },
    {
      "url": "https://www.k-bid.com/auction/62603/item/18",
      "itemName": "Error: Could not fetch",
      "currentPrice": "N/A",
      "timestamp": "2026-06-14T01:43:00.149Z",
      "error": "Request failed with status code 403"
    },
    {
      "url": "https://www.k-bid.com/auction/62603/item/2",
      "itemName": "Error: Could not fetch",
      "currentPrice": "N/A",
      "timestamp": "2026-06-14T01:43:08.232Z",
      "error": "Request failed with status code 403"
    }
  ]
}